console/__init__.py
console/secuer_console.py
secuer/__init__.py
secuer/secuer.py
secuer/secuerconsensus.py
secuer-1.0.7.dist-info/LICENSE.txt
secuer-1.0.7.dist-info/METADATA
secuer-1.0.7.dist-info/WHEEL
secuer-1.0.7.dist-info/entry_points.txt
secuer-1.0.7.dist-info/top_level.txt
secuer-1.0.7.dist-info/RECORD
