Metadata-Version: 2.1
Name: secuer
Version: 1.0.7
Summary: Secuer: ultrafast, scalable and accurate clustering of single-cell RNA-seq data
Home-page: https://github.com/nanawei11/Secuer
Author: nnwei
Author-email: nanawei11@163.com
License: MIT
License-File: LICENSE.txt
